HelloEdward/__init__.py
HelloEdward/core.py
helloedward-0.0.1.dist-info/METADATA
helloedward-0.0.1.dist-info/WHEEL
helloedward-0.0.1.dist-info/licenses/LICENSE.txt
helloedward-0.0.1.dist-info/RECORD
