Metadata-Version: 2.4
Name: HelloEdward
Version: 0.0.1
Summary: Publish my first pkg in my life
Project-URL: Homepage, https://github.com/edwardkao6413/HelloEdward
Project-URL: Issues, https://github.com/edwardkao6413/HelloEdward
Author-email: edwardkao6413 <edwardkao6413@gmail.com>
License:                     GNU GENERAL PUBLIC LICENSE
License-File: LICENSE.txt
Classifier: License :: OSI Approved :: GNU General Public License v3 (GPLv3)
Classifier: Operating System :: OS Independent
Classifier: Programming Language :: Python :: 3
Requires-Python: >=3.7
